cloudsecretmanager/__init__.py
cloudsecretmanager/azure.py
cloudsecretmanager/gcp.py
cloudsecretmanager/secret_manager.py
cloudsecretmanager-0.2.2.dist-info/METADATA
cloudsecretmanager-0.2.2.dist-info/WHEEL
cloudsecretmanager-0.2.2.dist-info/RECORD
