Metadata-Version: 2.1
Name: cloudsecretmanager
Version: 0.2.2
Summary: A unified interface for managing secrets across multiple cloud providers. This package includes concrete implementations for Azure Key Vault and Google Cloud Secret Manager, providing a consistent and simplified API for secret creation, retrieval, and management. It is designed to facilitate secure and efficient secret handling in cloud-based applications, promoting best practices in secret management.
Home-page: https://github.com/zinyosrim/cloud-secret-manager
License: MIT
Author: Zin Yosrim
Author-email: zinyosrim@gmail.com
Requires-Python: >=3.9,<4.0
Classifier: Intended Audience :: Developers
Classifier: License :: OSI Approved :: MIT License
Classifier: Operating System :: OS Independent
Classifier: Programming Language :: Python :: 3
Classifier: Programming Language :: Python :: 3.9
Classifier: Programming Language :: Python :: 3.10
Classifier: Programming Language :: Python :: 3.11
Classifier: Topic :: Security
Classifier: Topic :: Software Development :: Libraries :: Python Modules
Requires-Dist: azure-identity (>=1.15.0,<2.0.0)
Requires-Dist: azure-keyvault-secrets (>=4.7.0,<5.0.0)
Requires-Dist: google-cloud-secret-manager (>=2.16.4,<3.0.0)
Project-URL: Repository, https://github.com/zinyosrim/cloud-secret-manager
